gameguardian_cli/__init__.py
gameguardian_cli/__main__.py
gameguardian_cli/cli.py
gameguardian_cli/dummyproc.py
gameguardian_cli/memeditor.py
gameguardian_cli/scanner.py
gameguardian_cli/utils.py
gameguardian_cli/valuetypes.py
gameguardian_cli/version.py
gameguardian_cli-1.0.dist-info/METADATA
gameguardian_cli-1.0.dist-info/WHEEL
gameguardian_cli-1.0.dist-info/entry_points.txt
gameguardian_cli-1.0.dist-info/top_level.txt
gameguardian_cli-1.0.dist-info/RECORD
