Metadata-Version: 2.4
Name: gameguardian-cli
Version: 1.0
Summary: Python CLI version of Game Guardian
Author: Dx4Grey
Requires-Python: >=3.6
Dynamic: author
Dynamic: requires-python
Dynamic: summary
